serialization_spec/__init__.py
serialization_spec/plugins.py
serialization_spec/serialization.py
serialization_spec/utils.py
django_rest_framework_serialization_spec-0.0.7.dist-info/LICENSE.txt
django_rest_framework_serialization_spec-0.0.7.dist-info/METADATA
django_rest_framework_serialization_spec-0.0.7.dist-info/WHEEL
django_rest_framework_serialization_spec-0.0.7.dist-info/top_level.txt
django_rest_framework_serialization_spec-0.0.7.dist-info/RECORD
